_annotation_tools/XML_CVAT.py
_annotation_tools/XML_CyberPSG.py
_annotation_tools/__init__.py
_annotation_tools/xml_structured_parsing/__init__.py
_annotation_tools/xml_structured_parsing/myXML.py
best/__init__.py
best/_config.py
best/feature.py
best/files.py
best/signal.py
best/stats.py
best/types.py
best/vector.py
best/annotations/CyberPSG.py
best/annotations/NSRR.py
best/annotations/__init__.py
best/annotations/analysis.py
best/annotations/correct.py
best/annotations/io.py
best/annotations/utils.py
best/annotations/visualisation.py
best/bids/__init__.py
best/bids/ied_detection.py
best/bids/utils.py
best/cloud/__init__.py
best/cloud/_db_connection_variables.py
best/cloud/_mefclient_connection_variables.py
best/cloud/db.py
best/cloud/mef.py
best/data_conversion/__init__.py
best/dbs/__init__.py
best/dbs/_generator.py
best/dbs/artifact_bank/RCS.mat
best/dbs/artifact_bank/RCSswitching.mat
best/dbs/artifact_bank/__init__.py
best/dbs/artifact_removal/__init__.py
best/dbs/artifact_removal/_remove_stimulation_artifacts.py
best/dbs/artifact_removal/dataset.py
best/dbs/artifact_removal/model.py
best/dbs/artifact_removal/trainer.py
best/dbs/artifact_removal/_configs/RCS_ArtifactEraser_250Hz_16.yaml
best/dbs/artifact_removal/_configs/RCS_ArtifactEraser_250Hz_32.yaml
best/dbs/artifact_removal/_configs/RCS_ArtifactEraser_250Hz_64.yaml
best/dbs/artifact_removal/_configs/RCS_ArtifactEraser_500Hz.yaml
best/dbs/artifact_removal/_configs/RCS_ArtifactEraser_500Hz_16.yaml
best/dbs/artifact_removal/_configs/RCS_ArtifactEraser_500Hz_32.yaml
best/dbs/artifact_removal/_configs/RCS_ArtifactEraser_500Hz_64.yaml
best/dbs/artifact_removal/_configs/RCS_ArtifactEraser_500Hz_RCS.yaml
best/dbs/artifact_removal/_configs/RCSswitching_ArtifactEraser_250Hz_64.yaml
best/dbs/artifact_removal/_configs/RCSswitching_ArtifactEraser_500Hz_64.yaml
best/dbs/artifact_removal/_configs/__init__.py
best/dbs/artifact_removal/_models/RCS_ArtifactEraser_250Hz_16.pt
best_toolbox-0.1.0.dist-info/LICENSE
best_toolbox-0.1.0.dist-info/METADATA
best_toolbox-0.1.0.dist-info/WHEEL
best_toolbox-0.1.0.dist-info/top_level.txt
best_toolbox-0.1.0.dist-info/RECORD
